mddocs/__init__.py
mddocs/__main__.py
mddocs/exceptions.py
mddocs/plugins.py
mddocs/relative_path_ext.py
mddocs/theme.py
mddocs/commands/__init__.py
mddocs/commands/build.py
mddocs/commands/gh_deploy.py
mddocs/commands/new.py
mddocs/commands/serve.py
mddocs/config/__init__.py
mddocs/config/base.py
mddocs/config/config_options.py
mddocs/config/defaults.py
mddocs/contrib/__init__.py
mddocs/contrib/search/__init__.py
mddocs/contrib/search/prebuild-index.js
mddocs/contrib/search/search_index.py
mddocs/contrib/search/lunr-language/lunr.da.js
mddocs/contrib/search/lunr-language/lunr.de.js
mddocs/contrib/search/lunr-language/lunr.du.js
mddocs/contrib/search/lunr-language/lunr.es.js
mddocs/contrib/search/lunr-language/lunr.fi.js
mddocs/contrib/search/lunr-language/lunr.fr.js
mddocs/contrib/search/lunr-language/lunr.hu.js
mddocs/contrib/search/lunr-language/lunr.it.js
mddocs/contrib/search/lunr-language/lunr.jp.js
mddocs/contrib/search/lunr-language/lunr.multi.js
mddocs/contrib/search/lunr-language/lunr.no.js
mddocs/contrib/search/lunr-language/lunr.pt.js
mddocs/contrib/search/lunr-language/lunr.ro.js
mddocs/contrib/search/lunr-language/lunr.ru.js
mddocs/contrib/search/lunr-language/lunr.stemmer.support.js
mddocs/contrib/search/lunr-language/lunr.sv.js
mddocs/contrib/search/lunr-language/lunr.th.js
mddocs/contrib/search/lunr-language/lunr.tr.js
mddocs/contrib/search/templates/search/lunr.js
mddocs/contrib/search/templates/search/main.js
mddocs/contrib/search/templates/search/worker.js
mddocs/structure/__init__.py
mddocs/structure/files.py
mddocs/structure/nav.py
mddocs/structure/pages.py
mddocs/structure/toc.py
mddocs/templates/sitemap.xml
mddocs/themes/__init__.py
mddocs/themes/mddocs/404.html
mddocs/themes/mddocs/__init__.py
mddocs/themes/mddocs/base.html
mddocs/themes/mddocs/content.html
mddocs/themes/mddocs/keyboard-modal.html
mddocs/themes/mddocs/main.html
mddocs/themes/mddocs/mddocs_theme.yml
mddocs/themes/mddocs/nav-sub.html
mddocs/themes/mddocs/search-modal.html
mddocs-1.0.4.dist-info/LICENSE
mddocs-1.0.4.dist-info/METADATA
mddocs-1.0.4.dist-info/WHEEL
mddocs-1.0.4.dist-info/entry_points.txt
mddocs-1.0.4.dist-info/top_level.txt
mddocs-1.0.4.dist-info/RECORD
